databaser/__init__.py
databaser/data_model.py
databaser/databaser.py
databaser/factory.py
databaser/m2m_model.py
databaser/pgsql.py
databaser/tests.py
databaser/transaction.py
databaser/__pycache__/databaser.cpython-38.pyc
databaser/__pycache__/pgsql.cpython-38.pyc
databaser/__pycache__/tests.cpython-38.pyc
databaser/db_parser/__init__.py
databaser/db_parser/__pycache__/__init__.cpython-38.pyc
databaser/db_parser/database/__init__.py
databaser/db_parser/database/create_database.py
databaser/db_parser/database/create_schema.py
databaser/db_parser/database/drop_database.py
databaser/db_parser/database/drop_schema.py
databaser/db_parser/database/__pycache__/__init__.cpython-38.pyc
databaser/db_parser/database/__pycache__/create_database.cpython-38.pyc
databaser/db_parser/database/__pycache__/drop_database.cpython-38.pyc
databaser/db_parser/table_data/__init__.py
databaser/db_parser/table_data/condition_parser.py
databaser/db_parser/table_data/delete.py
databaser/db_parser/table_data/field_parser.py
databaser/db_parser/table_data/finder.py
databaser/db_parser/table_data/insert.py
databaser/db_parser/table_data/insert_from_select.py
databaser/db_parser/table_data/join_parser.py
databaser/db_parser/table_data/update.py
databaser/db_parser/table_structure/__init__.py
databaser/db_parser/table_structure/add_column.py
databaser/db_parser/table_structure/create_table.py
databaser/db_parser/table_structure/drop_table.py
databaser/db_parser/table_structure/references_fk.py
databaser/engine/__init__.py
databaser/engine/engine.py
databaser/engine/result.py
databaser/validation/__init__.py
databaser/validation/field.py
databaser-0.9.41.dist-info/METADATA
databaser-0.9.41.dist-info/WHEEL
databaser-0.9.41.dist-info/top_level.txt
databaser-0.9.41.dist-info/RECORD
