Metadata-Version: 2.1
Name: databaser
Version: 0.9.41
Summary: A small package to generate SQL for postgreSQL
Home-page: https://github.com/alymohamedhassan/databaser
Author: Aly Mohamed Hassan
Author-email: alyhassan10@hotmail.com
Project-URL: Bug Tracker, https://github.com/alymohamedhassan/databaser/issues
Classifier: Programming Language :: Python :: 3
Classifier: License :: OSI Approved :: Apache Software License
Classifier: Operating System :: OS Independent
Requires-Python: >=3.6
Requires-Dist: pymssql
Requires-Dist: psycopg2
Requires-Dist: pydantic
Requires-Dist: function
